setup.py
tic_tac_toe_two_players/__init__.py
tic_tac_toe_two_players/tic_tac_toe_two_players.py
tic_tac_toe_two_players.egg-info/PKG-INFO
tic_tac_toe_two_players.egg-info/SOURCES.txt
tic_tac_toe_two_players.egg-info/dependency_links.txt
tic_tac_toe_two_players.egg-info/not-zip-safe
tic_tac_toe_two_players.egg-info/top_level.txt