Metadata-Version: 1.0
Name: tic-tac-toe-two-players
Version: 0.1
Summary: Game Tic Tac Toe for two players
Home-page: UNKNOWN
Author: Melanija Gerasimovska
Author-email: melanija_gerasimovska@hotmail.com
License: UNKNOWN
Platform: UNKNOWN
